dtb/currency/__init__.py
dtb/currency/conftest.py
dtb/currency/currency.py
dtb/currency/currency.pyi
dtb/currency/errors.py
dtb/currency/py.typed
dtb/currency/test.py
dtb.currency-1.3.0.dist-info/WHEEL
dtb.currency-1.3.0.dist-info/METADATA
dtb.currency-1.3.0.dist-info/RECORD
